odoo/addons/crm_sale_automatic_quotation_asynchronous_wizard/README.rst
odoo/addons/crm_sale_automatic_quotation_asynchronous_wizard/__init__.py
odoo/addons/crm_sale_automatic_quotation_asynchronous_wizard/__manifest__.py
odoo/addons/crm_sale_automatic_quotation_asynchronous_wizard/i18n/es.po
odoo/addons/crm_sale_automatic_quotation_asynchronous_wizard/readme/CONFIGURE.md
odoo/addons/crm_sale_automatic_quotation_asynchronous_wizard/readme/CONTRIBUTORS.md
odoo/addons/crm_sale_automatic_quotation_asynchronous_wizard/readme/DESCRIPTION.md
odoo/addons/crm_sale_automatic_quotation_asynchronous_wizard/readme/INSTALL.md
odoo/addons/crm_sale_automatic_quotation_asynchronous_wizard/readme/USAGE.md
odoo/addons/crm_sale_automatic_quotation_asynchronous_wizard/static/description/icon.png
odoo/addons/crm_sale_automatic_quotation_asynchronous_wizard/static/description/index.html
odoo/addons/crm_sale_automatic_quotation_asynchronous_wizard/tests/__init__.py
odoo/addons/crm_sale_automatic_quotation_asynchronous_wizard/tests/test_crm_sale_automatic_quotation_asynchronous_wizard.py
odoo/addons/crm_sale_automatic_quotation_asynchronous_wizard/wizards/__init__.py
odoo/addons/crm_sale_automatic_quotation_asynchronous_wizard/wizards/crm_sale_automatic_quotation_wizard.py
odoo/addons/crm_sale_automatic_quotation_asynchronous_wizard/wizards/crm_sale_automatic_quotation_wizard.xml
odoo_addon_crm_sale_automatic_quotation_asynchronous_wizard-18.0.1.0.0.dist-info/METADATA
odoo_addon_crm_sale_automatic_quotation_asynchronous_wizard-18.0.1.0.0.dist-info/WHEEL
odoo_addon_crm_sale_automatic_quotation_asynchronous_wizard-18.0.1.0.0.dist-info/top_level.txt
odoo_addon_crm_sale_automatic_quotation_asynchronous_wizard-18.0.1.0.0.dist-info/RECORD
