Metadata-Version: 2.1
Name: odoo-addon-crm_sale_automatic_quotation_asynchronous_wizard
Version: 18.0.1.0.0
Requires-Python: >=3.10
Requires-Dist: odoo-addon-crm_sale_automatic_quotation==18.0.*
Requires-Dist: odoo-addon-queue_job==18.0.*
Requires-Dist: odoo==18.0.*
Summary: Speed up the CRM Sale Automatic Quotation Wizard
Home-page: https://github.com/sygel-technology/sy-crm
License: AGPL-3
Author: Sygel, Odoo Community Association (OCA)
Author-email: support@odoo-community.org
Classifier: Programming Language :: Python
Classifier: Framework :: Odoo
Classifier: Framework :: Odoo :: 18.0
Classifier: License :: OSI Approved :: GNU Affero General Public License v3
